stomatadetector/__init__.py
stomatadetector/filebrowser.py
stomatadetector/flexmetadata.py
stomatadetector/stomataobjects.py
stomatadetector-0.0.7.dev0.dist-info/LICENSE
stomatadetector-0.0.7.dev0.dist-info/METADATA
stomatadetector-0.0.7.dev0.dist-info/WHEEL
stomatadetector-0.0.7.dev0.dist-info/top_level.txt
stomatadetector-0.0.7.dev0.dist-info/RECORD
