Metadata-Version: 2.1
Name: stomatadetector
Version: 0.0.7.dev0
Summary: Stomata detection from FLEX/TIFF fluorescent images
Home-page: https://github.com/TeamMacLean/stomatameasurer
Author: Dan MacLean
Author-email: dan.maclean@tsl.ac.uk
License: MIT
Platform: UNKNOWN
Classifier: Development Status :: 3 - Alpha
Classifier: License :: OSI Approved :: MIT License
Classifier: Programming Language :: Python :: 3.5
Classifier: Topic :: Scientific/Engineering :: Image Recognition
Requires-Dist: numpy
Requires-Dist: scipy
Requires-Dist: scikit-image
Requires-Dist: matplotlib
Requires-Dist: ipywidgets
Requires-Dist: xmltodict
Requires-Dist: tifffile
